{
  "诗经 Glossary - Proper nouns and essential vocabulary": [],
  "These words are explicitly taught in the graded reader and excluded from the 95/5 count.": [],
  "Book title and sections": [
    "诗经",
    "诗三百"
  ],
  "Section names (风雅颂)": [
    "国风",
    "风雅颂",
    "小雅",
    "大雅",
    "周颂",
    "鲁颂",
    "商颂"
  ],
  "Poetry techniques": [
    "赋比兴"
  ],
  "Historical references": [
    "周朝",
    "周代",
    "西周",
    "东周",
    "周公",
    "周南",
    "召南",
    "孔子",
    "孟子",
    "毛诗",
    "毛诗序",
    "诗序",
    "论语",
    "左传",
    "春秋",
    "郑风",
    "卫风",
    "王风",
    "秦风",
    "魏风",
    "豳风",
    "邶风",
    "鄘风",
    "齐风",
    "唐风",
    "陈风",
    "桧风",
    "曹风"
  ],
  "Poem titles": [
    "关雎",
    "蒹葭",
    "桃夭",
    "采薇",
    "硕鼠",
    "木瓜",
    "击鼓",
    "静女",
    "黍离",
    "氓",
    "伐檀",
    "七月",
    "鹿鸣",
    "卷耳",
    "芣苢",
    "子衿",
    "将仲子",
    "式微",
    "君子于役",
    "无衣"
  ],
  "Classical Chinese function words (appear in original poems)": [
    "之",
    "乎",
    "者",
    "也",
    "矣",
    "焉",
    "哉",
    "兮",
    "其",
    "何",
    "於",
    "若",
    "所",
    "以",
    "而",
    "则",
    "于",
    "与",
    "为",
    "乃",
    "遂",
    "虽",
    "故",
    "因",
    "且",
    "及",
    "即"
  ],
  "Key literary/cultural terms": [
    "祭祀",
    "君子",
    "淑女",
    "伊人",
    "佳人",
    "美人"
  ],
  "Poem-specific terms that recur": [
    "雎鸠",
    "窈窕",
    "逑",
    "蒹葭",
    "苍苍",
    "桃夭",
    "灼灼",
    "采薇",
    "硕鼠",
    "木瓜",
    "琼琚",
    "琼瑶",
    "琼玖",
    "击鼓",
    "镗镗",
    "静女",
    "俟",
    "城隅",
    "彤管",
    "荑"
  ],
  "Place names": [
    "黄河",
    "汉水",
    "洛水"
  ],
  "Dynasty/era terms": [
    "殷商",
    "商朝",
    "先秦",
    "战国"
  ]
}